ip2geo/__init__.py
ip2geo/client.py
ip2geoapi-1.0.0.dist-info/licenses/LICENSE
ip2geoapi-1.0.0.dist-info/METADATA
ip2geoapi-1.0.0.dist-info/WHEEL
ip2geoapi-1.0.0.dist-info/top_level.txt
ip2geoapi-1.0.0.dist-info/RECORD
