Metadata-Version: 2.4
Name: ip2geoapi
Version: 1.0.0
Summary: Official Python SDK for the Ip2Geo API
Author: Vijay Prajapati
License: MIT
Project-URL: Homepage, https://ip2geoapi.com
Project-URL: Documentation, https://ip2geoapi.com/docs
Project-URL: Source, https://github.com/vijaykrpp/ip2geo-python
Requires-Python: >=3.8
License-File: LICENSE
Requires-Dist: requests>=2.25
Dynamic: license-file
